{"basics":{"name":"Li Yayuan","label":"博士生","image":"","email":"liyayuan@smail.nju.edu.cn","url":"https://himuwu.com/resume/","summary":"Practitioner in the field of artificial intelligence.","location":{"address":"Dorm 21st, 163 Xianlin Street, Qixia Distirct","postalCode":"210023","city":"Nanjing","countryCode":"CN","region":"Jiangsu"}},"volunteer":[{"organization":"CCF Big Data","location":"Nanjing, China","position":"volunteer","url":"https://ccf.org.cn/BigData2023","startDate":"2023-09-08","endDate":"2023-09-10","summary":"Contributed to maintaining on-site order and coordinating transportation for participating experts."},{"organization":"Nanjing University","location":"Suzhou, China","position":"volunteer","url":"https://www.nju.edu.cn/info/3461/341221.htm","startDate":"2023-09-24","endDate":"2023-09-24","summary":"Contributed to maintaining on-site order."},{"organization":"Academic Divisions of the Chinese Academy of Sciences","location":"Nanjing, China","position":"volunteer","url":"https://academics.casad.cas.cn/xshd/kxyjsqylt/","startDate":"2024-01-06","endDate":"2024-01-07","summary":"Contributed to maintaining order and equipment in the sub-venue, as well as coordinating transportation for participating experts."}],"education":[{"institution":"Beijing Jiaotong University, Beijing, China","location":"Beijing, China","url":"https://www.bjtu.edu.cn/","area":"Computer Science","studyType":"Bachelor","startDate":"2019-09-01","endDate":"2023-06-30"},{"institution":"Nanjing University, Nanjing, China","location":"Nanjing, China","url":"https://www.nju.edu.cn/","area":"Computer Science","studyType":"Master","startDate":"2023-09-01","endDate":"2026-06-30"}],"awards":[{"title":"National Scholarship","date":"2022-10-01","awarder":"Ministry of Education of the People's Republic of China","url":"http://www.moe.gov.cn/jyb_xwfb/xw_zt/moe_357/jyzt_2015nztzl/2015_zt06/15zt06_gxzzzc/gxzz_bzks/201508/t20150810_199202.html","summary":"The National Scholarship is awarded to outstanding students in China for their academic excellence."}]}